ML_Translator/__init__.py
ML_Translator_6-0.0.1.dist-info/LICENCE.txt
ML_Translator_6-0.0.1.dist-info/METADATA
ML_Translator_6-0.0.1.dist-info/WHEEL
ML_Translator_6-0.0.1.dist-info/top_level.txt
ML_Translator_6-0.0.1.dist-info/RECORD
