Metadata-Version: 2.1
Name: ML-Translator-6
Version: 0.0.1
Summary: A Docx File Translator Using ML
Home-page: 
Author: Ambreshrc
Author-email: ambreshrc23@gmail.com
License: MIT
Keywords: ML_Translator,Translator,Ambreshrc,Ambresh
Classifier: Development Status :: 5 - Production/Stable
Classifier: Intended Audience :: Education
Classifier: Operating System :: Microsoft :: Windows :: Windows 10
Classifier: License :: OSI Approved :: MIT License
Classifier: Programming Language :: Python :: 3
License-File: LICENCE.txt
Requires-Dist: sentencepiece
Requires-Dist: torch
Requires-Dist: torchvision
Requires-Dist: torchaudio
Requires-Dist: transformers
Requires-Dist: python-docx
Requires-Dist: sacremoses
Requires-Dist: nltk
Requires-Dist: tqdm
